slidecompress.py
slidecompress-0.1.4.dist-info/METADATA
slidecompress-0.1.4.dist-info/WHEEL
slidecompress-0.1.4.dist-info/entry_points.txt
slidecompress-0.1.4.dist-info/RECORD
