Metadata-Version: 2.4
Name: slidecompress
Version: 0.1.4
Summary: Compress PowerPoint presentations by optimizing embedded images
Project-URL: Homepage, https://github.com/sanand0/slidecompress
Author-email: S Anand <root.node@gmail.com>
License: MIT
Keywords: compression,images,optimization,powerpoint
Classifier: Development Status :: 4 - Beta
Classifier: Intended Audience :: End Users/Desktop
Classifier: License :: OSI Approved :: MIT License
Classifier: Programming Language :: Python :: 3
Classifier: Programming Language :: Python :: 3.8
Classifier: Topic :: Office/Business :: Office Suites
Requires-Python: >=3.8
